blastp_xml_parser/__init__.py
blastp_xml_parser/blastp_xml_parser.py
blastp_xml_parser-0.1.dist-info/METADATA
blastp_xml_parser-0.1.dist-info/WHEEL
blastp_xml_parser-0.1.dist-info/top_level.txt
blastp_xml_parser-0.1.dist-info/RECORD
