Metadata-Version: 2.1
Name: blastp-xml-parser
Version: 0.1
Summary: blastp_xml_parser
Home-page: https://github.com/esbusis/blastp_xml_parser.git
Author: esbusis
Author-email: esbusraisik@gmail.com
License: MIT
Platform: UNKNOWN
Requires-Dist: biopython
Requires-Dist: pandas
Requires-Dist: more-itertools
